naive_stopwords/__init__.py
naive_stopwords/files.py
naive_stopwords/stopwords.py
naive_stopwords/stopwords_test.py
naive_stopwords/data/baidu_stopwords.txt
naive_stopwords/data/cn_stopwords.txt
naive_stopwords/data/hit_stopwords.txt
naive_stopwords/data/jieba.stopwords.txt
naive_stopwords/data/scu_stopwords.txt
naive_stopwords-0.0.2.dist-info/LICENSE
naive_stopwords-0.0.2.dist-info/METADATA
naive_stopwords-0.0.2.dist-info/WHEEL
naive_stopwords-0.0.2.dist-info/top_level.txt
naive_stopwords-0.0.2.dist-info/RECORD
